{
"document" : {
"data" : {
"NAME" : "GROUP_ALIASES_TABLE",
"COMMENT" : "Default Backbone.",
"AUTHOR" : "admin",
"CREATION_TIME" : 1582060258,
"COL_TYPES" : {
"GROUP_KEY_ALIAS" : "STRING",
"GROUP_NAME" : "STRING",
"GROUP_KEY" : "STRING",
"COMMENT_DESCRIPTION" : "STRING",
"AUTHOR" : "STRING",
"RECORD_INSERTION_TIME" : "TIMESTAMP WITH TIMEZONE"
},
"DATA_SET" : [
{
"GROUP_KEY_ALIAS" : "MasterContext",
"GROUP_NAME" : "T992Context",
"GROUP_KEY" : "13",
"COMMENT_DESCRIPTION" : "This Group Alias was automatically setup by the server.",
"AUTHOR" : "admin",
"RECORD_INSERTION_TIME" : "1582060257"
},
{
"GROUP_KEY_ALIAS" : "T992Config",
"GROUP_NAME" : "T992Config",
"GROUP_KEY" : "10",
"COMMENT_DESCRIPTION" : "This Group Alias was automatically setup by the server.",
"AUTHOR" : "admin",
"RECORD_INSERTION_TIME" : "1582059936"
},
{
"GROUP_KEY_ALIAS" : "SlaveContext",
"GROUP_NAME" : "T992Context",
"GROUP_KEY" : "3",
"COMMENT_DESCRIPTION" : "This Group Alias was automatically setup by the server.",
"AUTHOR" : "admin",
"RECORD_INSERTION_TIME" : "1542386340"
}
]
},
"metadata" : {

},
"search" : [

]
},
"comments" : [

],
"origin" : {
"source" : "template",
"name" : "notprovided",
"format" : "json",
"created" : "2020-02-18T15:10:58.013-0600",
"rawdata" : [

]
},
"version" : "22",
"entities" : [
{
"name" : "OTSROOT",
"assigned" : "2020-02-18T15:10:58.014-0600"
}
],
"configurations" : [
{
"name" : "notprovided",
"assigned" : "2020-02-18T15:10:58.014-0600"
},
{
"name" : "GroupAliasTreeEditWizBackbone_v16",
"assigned" : "2020-02-18T15:10:58.741-0600"
}
],
"changelog" : "notprovided",
"bookkeeping" : {
"isdeleted" : false,
"isreadonly" : false,
"updates" : [
{
"event" : "addConfiguration",
"timestamp" : "2020-02-18T15:10:58.014-0600",
"value" : {
"name" : "notprovided",
"assigned" : "2020-02-18T15:10:58.014-0600"
}
},
{
"event" : "setVersion",
"timestamp" : "2020-02-18T15:10:58.014-0600",
"value" : {
"name" : "22",
"assigned" : "2020-02-18T15:10:58.014-0600"
}
},
{
"event" : "setCollection",
"timestamp" : "2020-02-18T15:10:58.014-0600",
"value" : {
"name" : "GroupAliasesTable",
"assigned" : "2020-02-18T15:10:58.014-0600"
}
},
{
"event" : "addEntity",
"timestamp" : "2020-02-18T15:10:58.014-0600",
"value" : {
"name" : "OTSROOT",
"assigned" : "2020-02-18T15:10:58.014-0600"
}
},
{
"event" : "addConfiguration",
"timestamp" : "2020-02-18T15:10:58.741-0600",
"value" : {
"name" : "GroupAliasTreeEditWizBackbone_v16",
"assigned" : "2020-02-18T15:10:58.741-0600"
}
}
],
"created" : "2020-02-18T15:10:58.013-0600"
},
"_id" : {
"$oid" : "99837447519c460d86e46c7e"
},
"collection" : "GroupAliasesTable",
"aliases" : {
"active" : [

],
"history" : [

]
},
"runs" : [

],
"attachments" : [

],
"configtype" : "notprovided"
}