{
"document" : {
"data" : {
"NAME" : "GROUP_ALIASES_TABLE",
"COMMENT" : "Default Backbone.",
"AUTHOR" : "admin",
"CREATION_TIME" : 1643234701,
"COL_TYPES" : {
"GROUP_KEY_ALIAS" : "STRING",
"GROUP_NAME" : "STRING",
"GROUP_KEY" : "STRING",
"COMMENT_DESCRIPTION" : "STRING",
"AUTHOR" : "STRING",
"RECORD_INSERTION_TIME" : "TIMESTAMP WITH TIMEZONE"
},
"DATA_SET" : [
{
"GROUP_KEY_ALIAS" : "MasterContext",
"GROUP_NAME" : "T992Context",
"GROUP_KEY" : "62",
"COMMENT_DESCRIPTION" : "This Group Alias was automatically setup by the server.",
"AUTHOR" : "admin",
"RECORD_INSERTION_TIME" : "1643230126"
},
{
"GROUP_KEY_ALIAS" : "T992Config",
"GROUP_NAME" : "T992Config",
"GROUP_KEY" : "182",
"COMMENT_DESCRIPTION" : "This Group Alias was automatically setup by the server.",
"AUTHOR" : "admin",
"RECORD_INSERTION_TIME" : "1643234701"
},
{
"GROUP_KEY_ALIAS" : "SlaveContext",
"GROUP_NAME" : "T992Context",
"GROUP_KEY" : "3",
"COMMENT_DESCRIPTION" : "This Group Alias was automatically setup by the server.",
"AUTHOR" : "admin",
"RECORD_INSERTION_TIME" : "1542386340"
}
]
},
"metadata" : {

},
"search" : [

]
},
"comments" : [

],
"origin" : {
"source" : "template",
"name" : "notprovided",
"format" : "json",
"created" : "2022-01-26T16:05:01.476-0600",
"rawdata" : [

]
},
"version" : "258",
"entities" : [
{
"name" : "OTSROOT",
"assigned" : "2022-01-26T16:05:01.476-0600"
}
],
"configurations" : [
{
"name" : "notprovided",
"assigned" : "2022-01-26T16:05:01.476-0600"
},
{
"name" : "GroupAliasTreeEditWizBackbone_v135",
"assigned" : "2022-01-26T16:05:04.393-0600"
}
],
"changelog" : "notprovided",
"bookkeeping" : {
"isdeleted" : false,
"isreadonly" : false,
"updates" : [
{
"event" : "addConfiguration",
"timestamp" : "2022-01-26T16:05:01.476-0600",
"value" : {
"name" : "notprovided",
"assigned" : "2022-01-26T16:05:01.476-0600"
}
},
{
"event" : "setVersion",
"timestamp" : "2022-01-26T16:05:01.476-0600",
"value" : {
"name" : "258",
"assigned" : "2022-01-26T16:05:01.476-0600"
}
},
{
"event" : "setCollection",
"timestamp" : "2022-01-26T16:05:01.476-0600",
"value" : {
"name" : "GroupAliasesTable",
"assigned" : "2022-01-26T16:05:01.476-0600"
}
},
{
"event" : "addEntity",
"timestamp" : "2022-01-26T16:05:01.476-0600",
"value" : {
"name" : "OTSROOT",
"assigned" : "2022-01-26T16:05:01.476-0600"
}
},
{
"event" : "addConfiguration",
"timestamp" : "2022-01-26T16:05:04.393-0600",
"value" : {
"name" : "GroupAliasTreeEditWizBackbone_v135",
"assigned" : "2022-01-26T16:05:04.393-0600"
}
}
],
"created" : "2022-01-26T16:05:01.476-0600"
},
"_id" : {
"$oid" : "4b263dfbd72b425f8c2f31eb"
},
"collection" : "GroupAliasesTable",
"aliases" : {
"active" : [

],
"history" : [

]
},
"runs" : [

],
"attachments" : [

],
"configtype" : "notprovided"
}